pylogalert/__init__.py
pylogalert/_core.py
pylogalert/notify.py
pylogalert/notify_ses.py
pylogalert/notify_slack.py
pylogalert/py.typed
pylogalert-0.1.6.1.dist-info/METADATA
pylogalert-0.1.6.1.dist-info/WHEEL
pylogalert-0.1.6.1.dist-info/licenses/LICENSE
pylogalert-0.1.6.1.dist-info/RECORD
